{
  "categories": [
    "Matt",
    "Bill",
    "Luke",
    "Leon",
    "Darrin",
    "Chad",
    "Frank",
    "Phil",
    "Dave",
    "Joe",
    "Gerry"
  ],
  "data": {
    "GP": [
      301,
      304,
      306,
      274,
      283,
      264,
      296,
      299,
      307,
      239,
      288
    ],
    "G": [
      84,
      94,
      107,
      87,
      85,
      88,
      83,
      84,
      87,
      79,
      66
    ],
    "A": [
      173,
      139,
      122,
      136,
      138,
      134,
      136,
      128,
      125,
      130,
      118
    ],
    "TP": [
      257,
      233,
      229,
      223,
      223,
      222,
      219,
      212,
      212,
      209,
      184
    ],
    "PPG": [
      "0.854",
      "0.766",
      "0.748",
      "0.814",
      "0.788",
      "0.841",
      "0.740",
      "0.709",
      "0.691",
      "0.874",
      "0.639"
    ],
    "o/nGP": [
      8,
      6,
      7,
      5,
      8,
      5,
      7,
      5,
      8,
      4,
      9
    ],
    "o/nTP": [
      8,
      6,
      4,
      2,
      2,
      8,
      1,
      3,
      7,
      3,
      7
    ],
    "PT": [
      1,
      4,
      5,
      3,
      4,
      5,
      3,
      6,
      6,
      5,
      2
    ]
  }
}