{
  "categories": [
    "Phil",
    "Joe",
    "Chad",
    "Leon",
    "Bill",
    "Dave",
    "Matt",
    "Darrin",
    "Luke",
    "Frank",
    "Gerry"
  ],
  "data": {
    "GP": [
      855,
      855,
      822,
      862,
      886,
      875,
      847,
      839,
      828,
      846,
      860
    ],
    "G": [
      279,
      303,
      263,
      256,
      273,
      237,
      234,
      266,
      281,
      249,
      242
    ],
    "A": [
      445,
      412,
      441,
      442,
      414,
      440,
      438,
      395,
      357,
      384,
      385
    ],
    "TP": [
      724,
      715,
      704,
      698,
      687,
      677,
      672,
      661,
      638,
      633,
      627
    ],
    "PPG": [
      "0.847",
      "0.836",
      "0.856",
      "0.810",
      "0.775",
      "0.774",
      "0.793",
      "0.788",
      "0.771",
      "0.748",
      "0.729"
    ],
    "o/nGP": [
      12,
      10,
      9,
      13,
      13,
      13,
      12,
      13,
      9,
      11,
      12
    ],
    "o/nTP": [
      10,
      7,
      3,
      11,
      15,
      14,
      10,
      10,
      8,
      9,
      6
    ],
    "PT": [
      5,
      6,
      6,
      3,
      4,
      4,
      6,
      3,
      5,
      5,
      2
    ]
  }
}