{
  "categories": [
    "Frank",
    "Joe",
    "Luc",
    "Luke",
    "Dave",
    "Matt",
    "Chad",
    "Phil",
    "Gerry",
    "Leon",
    "Darrin",
    "Bill"
  ],
  "data": {
    "GP": [
      877,
      898,
      895,
      926,
      908,
      888,
      857,
      909,
      909,
      904,
      884,
      898
    ],
    "G": [
      258,
      279,
      279,
      272,
      272,
      266,
      274,
      250,
      291,
      241,
      239,
      230
    ],
    "A": [
      458,
      424,
      422,
      427,
      418,
      423,
      402,
      416,
      370,
      415,
      415,
      379
    ],
    "TP": [
      716,
      703,
      701,
      699,
      690,
      689,
      676,
      666,
      661,
      656,
      654,
      609
    ],
    "PPG": [
      "0.816",
      "0.783",
      "0.783",
      "0.755",
      "0.760",
      "0.776",
      "0.789",
      "0.733",
      "0.727",
      "0.726",
      "0.740",
      "0.678"
    ],
    "o/nGP": [
      12,
      14,
      10,
      15,
      10,
      13,
      12,
      14,
      12,
      10,
      9,
      9
    ],
    "o/nTP": [
      13,
      10,
      3,
      5,
      8,
      11,
      7,
      8,
      7,
      2,
      5,
      4
    ],
    "PT": [
      9,
      3,
      6,
      3,
      7,
      8,
      10,
      5,
      7,
      7,
      5,
      8
    ]
  }
}