{
  "categories": [
    "Phil",
    "Matt",
    "Leon",
    "Joe",
    "Bill",
    "Darrin",
    "Luke",
    "Dave",
    "Chad",
    "Frank",
    "Gerry"
  ],
  "data": {
    "GP": [
      640,
      631,
      614,
      562,
      597,
      591,
      611,
      630,
      521,
      583,
      598
    ],
    "G": [
      190,
      177,
      176,
      183,
      182,
      166,
      199,
      160,
      167,
      162,
      146
    ],
    "A": [
      291,
      301,
      281,
      271,
      267,
      277,
      233,
      269,
      258,
      259,
      252
    ],
    "TP": [
      481,
      478,
      457,
      454,
      449,
      443,
      432,
      429,
      425,
      421,
      398
    ],
    "PPG": [
      "0.752",
      "0.758",
      "0.744",
      "0.808",
      "0.752",
      "0.750",
      "0.707",
      "0.681",
      "0.816",
      "0.722",
      "0.666"
    ],
    "o/nGP": [
      5,
      7,
      7,
      6,
      5,
      5,
      0,
      6,
      4,
      4,
      7
    ],
    "o/nTP": [
      4,
      4,
      2,
      4,
      0,
      3,
      0,
      3,
      1,
      3,
      4
    ],
    "PT": [
      5,
      7,
      8,
      6,
      6,
      7,
      0,
      7,
      4,
      5,
      7
    ]
  }
}